dummy_package_manager/__init__.py
dummy_package_manager/core.py
dummy_package_manager-0.1.0.dist-info/LICENSE
dummy_package_manager-0.1.0.dist-info/METADATA
dummy_package_manager-0.1.0.dist-info/WHEEL
dummy_package_manager-0.1.0.dist-info/top_level.txt
dummy_package_manager-0.1.0.dist-info/RECORD
