Metadata-Version: 2.1
Name: dummy-package-manager
Version: 0.1.0
Summary: A utility for creating and managing dummy Python packages with optional dependencies.
Home-page: https://github.com/eftalgezer/dummy_package_manager
Author: Eftal Gezer
Author-email: eftal.gezer@astrobiyoloji.org
Project-URL: Bug Reports, https://github.com/eftalgezer/dummy_package_manager/issues
Project-URL: Source, https://github.com/eftalgezer/dummy_package_manager
Project-URL: Blog, https://beyondthearistotelian.blogspot.com/search/label/dummy_package_manager
Project-URL: Developer, https://www.eftalgezer.com/
Keywords: dummy package,dummy,package,utility,dependencies,testing
Classifier: Development Status :: 5 - Production/Stable
Classifier: Intended Audience :: Developers
Classifier: Intended Audience :: Science/Research
Classifier: Operating System :: MacOS
Classifier: Operating System :: Microsoft :: Windows
Classifier: Operating System :: OS Independent
Classifier: Operating System :: POSIX :: Linux
Classifier: Programming Language :: Python :: 3.7
Classifier: Programming Language :: Python :: 3.8
Classifier: Programming Language :: Python :: 3.9
Classifier: Programming Language :: Python :: 3.10
Classifier: Programming Language :: Python :: 3.11
Classifier: Programming Language :: Python :: 3.12
Classifier: Topic :: Education :: Testing
Classifier: Topic :: Scientific/Engineering
Classifier: Topic :: Software Development
Classifier: Topic :: Software Development :: Testing
Classifier: Topic :: Utilities
License-File: LICENSE
Requires-Dist: pip
